{
  "layout": {
    "title": "Owner Landing",
    "appColor": "white",
    "backgroundColor": "white"
  },
  "children": [
    {
      "component": "Container",
      "props": {
        "flexDirection": "column",
        "alignItems": "center",
        "justifyContent": "center",
        "flex": 1,
        "height": "100%",
        "maxWidth": 700
      },
      "children": [
        {
            "component": "Box",
            "props": {
                "padding": 40
            },
            "children": [
                {
                    "component": "Image",
                    "props": {
                        "height": 220,
                        "width": 400,
                        "top": 50,
                        "source": "https://i.imgur.com/cHdr17N.jpg"
                    }
                }
            ]
        },
        {
          "component": "Box",
          "props": {
            "padding": 10
          },
          "children": [
            {
              "component": "Heading",
              "props": {
                "color": "#e05b9e",
                "size": "xxl",
                "bold": false
              },
              "children": "Thank You"
            }
          ]
        },
        {
          "component": "Box",
          "props": {
            "padding": 10
          },
          "children": [
            {
              "component": "Text",
              "props": {
                "size": "xs",
                "bold": false
              },
              "children": "Thank you for completing your details, we will be in touch as soon as possible."
            }
          ]
        }
      ]
    }
  ]
}
