{
  "barStyle": "light-content",
  "backgroundColor": "#232323",
  "paddingX": 5,
  "height": 60,
  "headerLeft": {
    "showTitle": true,
    "showMenu": true,
    "showBack": true
  },
  "headerRight": {
    "items": [
      {
        "id": "chat",
        "icon": "chat",
        "href": "chat",
        "platforms": ["ios", "web"]
      },
      {
        "id": "profile",
        "icon": "account-circle",
        "href": "/profile",
        "eventType": "PROFILE",
        "buttonCode": "PROFILE",
        "platforms": ["ios"]
      },
      {
        "id": "dropdown",
        "dropdown": true,
        "text": "{{user.attributes.PRI_FIRSTNAME.value}}",
        "platforms": ["android"],
        "items": [
          {
            "id": "profile",
            "href": "/profile",
            "icon": "person",
            "text": "Profile",
            "eventType": "PROFILE",
            "buttonCode": "PROFILE"
          },
          {
            "id": "logout",
            "icon": "power-settings-new",
            "href": "/logout",
            "text": "Logout"
          }
        ]
      },
      {
        "id": "dropdown",
        "dropdown": true,
        "text": "Hi, {{user.attributes.PRI_FIRSTNAME.value}}!",
        "platforms": ["web"],
        "items": [
          {
            "id": "profile",
            "href": "/profile",
            "icon": "person",
            "text": "Profile",
            "eventType": "PROFILE",
            "buttonCode": "PROFILE"

          },
          {
            "id": "logout",
            "icon": "power-settings-new",
            "href": "/logout",
            "text": "Logout"
          }
        ]
      }
    ]
  }
}
