{
  "layout": {
    "title": "Registration",
    "appColor": "red",
    "backgroundColor": "white",
    "header": {
      "variant": "public-transparent"
    }
  },
  "children": [
  {  
    "component":"Box",
    "props":{
      "flexDirection":"row"
    },
    "children": [
      {
          "component": "Container",
          "props": {
            "flexDirection" : "column"
          },
          "children": [
            {
                "component": "Box",
                "props": {
                  "flexDirection" : "row"
                },
                "children": [
                  {
                    "component": "Box",
                    "props": {
                      "paddingTop": "10px",
                      "padddingBottom": "10px",
                      "paddingLeft": "10px",
                      "paddingRight": "10px"
                    },
                    "children": [
                      {
                        "component": "Image",
                        "props": {
                          "source": "https://i.imgur.com/ziHkxPf.jpg",
                          "justifyContent":"center",
                          "flexDirection":"column",
                          "shape": "square",
                          "height":100,
                          "width":100
                        }
                      }
                    ]
                  },
                  {
                    "component": "Box",
                    "props": {
                      "flexDirection": "column"
                    },
                    "children": [
                      {
                        "component": "Box",
                        "props": {},
                        "children": [
                          {
                            "component": "Box",
                            "children": {
                              "component": "Text",
                              "children": "Devops Trainee",
                              "props": {
                                "color": "#49515d",
                                "size": "xl",
                                "fontFamily":"arial",
                                "paddingX": 0,
                                "paddingY": 0,
                                "marginX": 0,
                                "marginY": 0
                              }
                            },
                            "props": {
                              "color": "red",
                              "paddingTop": "10px"
                            }
                          }
                        ]
                      },
                      {
                        "component": "Box",
                        "props": {
                          "paddingTop": "5px"
                        },
                        "children": [
                          {
                            "component": "Box",
                            "children": {
                              "component": "Text",
                              "children": "Posted By: Dibs",
                              "props": {
                                "size": "sm",
                                "color": "#38444f",
                                "fontFamily":"arial",
                                "bold": "true"
                              }
                            },
                            "props": {
                              "paddingTop":"5px"
                            }
                          }
                        ]
                      },
                      {
                        "component": "Box",
                        "children": [
                          {
                            "component": "Box",
                            "children": {
                              "component": "Text",
                              "children": "Posted on :14 Aug 2018",
                              "props": {
                                "size": "xs",
                                "color": "#38444f",
                                "fontFamily":"arial"
                              }
                            },
                            "props": {
                              "paddingTop": "15px",
                              "paddingBottom": "10px"
                            }
                          }
                        ]
                      }
                    ]
                  }
                ]
            },
            {
              "component": "Box",
              "props": {
                "flexDirection": "row",
                "backgroundColor":"#D3D3D3",
                "height":80,
                "marginTop":20
              },
              "children": [
                {
                  "component": "Box",
                  "props": {
                    "flexDirection": "row",
                    "backgroundColor":"#D3D3D3",
                    "justifyContent":"center"
                  },
                  "children": [
                    {
                      "component": "Box",
                      "children": [
                        {
                          "component": "Icon",
                          "props": {
                          "name": "place",
                          "color":"black"
                          }
                        }
                    ],
                      "props": {
                        "flexDirection": "column",
                        "justifyContent": "center",
                        "height": 100,
                        "width":10,
                        "paddingLeft": 10,
                        "paddingRight":30
                      }
                    },
                    {
                      "component": "Box",
                      "props": {
                        "flexDirection": "column",
                        "justifyContent":"center"
                      },
                      "children": [
                        {
                          "component": "Box",
                          "props": {},
                          "children": [
                            {
                              "component": "Box",
                              "children": {
                                "component": "Text",
                                "children": "66 Fakenham Road, Ashburton,",
                                "props": {
                                  "color": "#49515d",
                                  "fontWeight": "bold"
                                }
                              },
                              "props": {
                                "paddingTop": "10px"
                              }
                            }
                          ]
                        },
                        {
                          "component": "Box",
                          "props": {
                            "paddingTop": "5px"
                          },
                          "children": [
                            {
                              "component": "Box",
                              "children": {
                                "component": "Text",
                                "children": "VIC, 3147, AU",
                                "props": {
                                  "color": "#38444f"
                                }
                              },
                              "props": {
                              }
                            }
                          ]
                        }
                      ]
                    }
                  ]
                },
                {
                  "component": "Box",
                  "props": {
                    "flexDirection": "row",
                    "backgroundColor":"#D3D3D3",
                    "paddingTop":"10px"
                  },
                  "children": [
                    {
                      "component": "Box",
                      "children": [
                        {
                          "component": "Icon",
                          "props": {
                          "name": "date_range",
                          "color":"black"
                          }
                        }
                    ],
                      "props": {
                        "flexDirection": "column",
                        "justifyContent": "center",
                        "paddingLeft": 80,
                        "paddingRight":10
                      }
                    },
                    {
                      "component": "Box",
                      "props": {
                        "flexDirection": "column",
                        "justifyContent":"center"
                      },
                      "children": [
                        {
                          "component": "Box",
                          "props": {
                          },
                          "children": [
                            {
                              "component": "Box",
                              "children": {
                                "component": "Text",
                                "children": "23 Aug 2018",
                                "props": {
                                  "color": "#38444f"
                                }
                              },
                              "props": {
                              }
                            }
                          ]
                        }
                      ]
                    }
                  ]
                },
                {
                  "component": "Box",
                  "props": {
                    "flexDirection": "row",
                    "backgroundColor":"#D3D3D3",
                    "paddingTop":"10px"
                  },
                  "children": [
                    {
                      "component": "Box",
                      "children": [
                        {
                          "component": "Icon",
                          "props": {
                          "name": "query_builder",
                          "color":"black"
                          }
                        }
                    ],
                      "props": {
                        "flexDirection": "column",
                        "justifyContent": "center",
                        "paddingLeft": 100,
                        "paddingRight":10
                      }
                    },
                    {
                      "component": "Box",
                      "props": {
                        "flexDirection": "column",
                        "justifyContent":"center"
                      },
                      "children": [
                        {
                          "component": "Box",
                          "props": {
                          },
                          "children": [
                            {
                              "component": "Box",
                              "children": {
                                "component": "Text",
                                "children": "12 Weeks",
                                "props": {
                                  "color": "#38444f"
                                }
                              },
                              "props": {
                              }
                            }
                          ]
                        }
                      ]
                    }
                  ]
                }
              ]
            },
            {
              "component": "Box",
              "props": {
                "height":80
              },
              "children": [
                {
                  "component": "Box",
                  "children": {
                    "component": "Text",
                    "children": "Host Company",
                    "props": {
                      "fontWeight": "bold"
                    }
                  },
                  "props": {
                    "width":"100%",
                    "justifyContent":"center",
                    "flexDirection":"column"
                  }
                }
              ]
            },
            {
              "component": "Box",
              "props": {
                "flexDirection": "column",
                "justifyContent":"space-between",
                "backgroundColor":"#D3D3D3",
                "height":100,
                "paddingBottom": "15px",
                "paddingTop": "15px"
    
              },
              "children": [
                {
                  "component": "Box",
                  "props": {
                    "flexDirection": "row",
                    "backgroundColor":"#D3D3D3"
                  },
                  "children": [
                    {
                      "component": "Box",
                      "children": [
                        {
                          "component": "Icon",
                          "props": {
                          "name": "person",
                          "color":"black"
                          }
                        }
                    ],
                      "props": {
                        "flexDirection": "column",
                        "justifyContent": "center",
                        "paddingLeft": 10,
                        "paddingRight":10
                      }
                    },
                    {
                      "component": "Box",
                      "props": {
                        "flexDirection": "column",
                        "justifyContent":"center"
                      },
                      "children": [
                        {
                          "component": "Box",
                          "props": {
                          },
                          "children": [
                            {
                              "component": "Box",
                              "children": {
                                "component": "Text",
                                "children": "Dibs",
                                "props": {
                                  "color": "#38444f"
                                }
                              },
                              "props": {
                              }
                            }
                          ]
                        }
                      ]
                    }
                  ]
                }, 
                {
                  "component": "Box",
                  "props": {
                    "flexDirection": "row",
                    "backgroundColor":"#D3D3D3"
                  },
                  "children": [
                    {
                      "component": "Box",
                      "children": [
                        {
                          "component": "Icon",
                          "props": {
                          "name": "email",
                          "color":"black"
                          }
                        }
                    ],
                      "props": {
                        "flexDirection": "column",
                        "justifyContent": "center",
                        "paddingLeft": 10,
                        "paddingRight":10
                      }
                    },
                    {
                      "component": "Box",
                      "props": {
                        "flexDirection": "column",
                        "justifyContent":"center"
                      },
                      "children": [
                        {
                          "component": "Box",
                          "props": {
                          },
                          "children": [
                            {
                              "component": "Box",
                              "children": {
                                "component": "Text",
                                "children": "dibs@gmail.com",
                                "props": {
                                  "color": "#38444f"
                                }
                              },
                              "props": {
                              }
                            }
                          ]
                        }
                      ]
                    }
                  ]
                },
                {
                  "component": "Box",
                  "props": {
                    "flexDirection": "row",
                    "backgroundColor":"#D3D3D3",
                    "padddingBottom":"10px"
                  },
                  "children": [
                    {
                      "component": "Box",
                      "children": [
                        {
                          "component": "Icon",
                          "props": {
                          "name": "call",
                          "color":"black"
                          }
                        }
                    ],
                      "props": {
                        "flexDirection": "column",
                        "justifyContent": "center",
                        "paddingLeft": 10,
                        "paddingRight":10
                      }
                    },
                    {
                      "component": "Box",
                      "props": {
                        "flexDirection": "column",
                        "justifyContent":"center"
                      },
                      "children": [
                        {
                          "component": "Box",
                          "props": {
                          },
                          "children": [
                            {
                              "component": "Box",
                              "children": {
                                "component": "Text",
                                "children": "0491570157",
                                "props": {
                                  "color": "#38444f"
                                }
                              },
                              "props": {
                              }
                            }
                          ]
                        }
                      ]
                    }
                  ]
                }
              ]
            },
            {
              "component": "Box",
              "props": {
                "height": 25,
                "backgroundColor":"white"
              }
            },
            {
              "component": "Box",
              "props": {
                "height": 2,
                "backgroundColor":"black"
              }
            },
            {
              "component": "Box",
              "children": [
                {
                  "component": "Text",
                  "props": {
                    "size": "xs",
                    "color": "#696969",
                    "fontFamily":"arial",
                    "bold":"true"
                  },
                  "children": "SKILLS"
                }
              ],
              "props": {
                "flexDirection": "column",
                "justifyContent": "center",
                "height": 27
              }
            },
            {
              "component": "Box",
              "props": {
                "height": 2,
                "backgroundColor":"black"
              }
            },
            {
              "component": "Box",
              "props": {
                "width":"100%",
                "backgroundColor":"white",
                "height":75
              },
              "children": [
                {
                  "component": "Box",
                  "props": {
                    "flexDirection": "row",
                    "justifyContent": "center"
                  },
                  "children": [
                    {
                      "component": "Button",
                      "props": {
                        "marginRight": "5px",
                        "size": "sm",
                        "fontFamily":"arial",
                        "borderColor":"darkgray",
                        "marginTop":10,
                        "text":"DOCKER",
                        "fontWeight": "lighter",
                        "borderWidth":2,
                        "height": 50,
                        "width": 80
                      }
                    },
                    {
                      "component": "Button",
                      "props": {
                        "size": "sm",
                        "fontWeight": "lighter",
                        "fontFamily":"arial",
                        "marginTop":10,
                        "borderColor":"darkgray",
                        "borderWidth":2,
                        "text":"SCRIPTING",
                        "height": 50,
                        "width": 90
                      }
                    }
                  ]
                }
              ]
            },
            {
              "component": "Box",
              "props": {
                "height": 2,
                "backgroundColor":"black"
              }
            },
            {
              "component": "Box",
              "children": [
                {
                  "component": "Text",
                  "props": {
                    "size": "xs",
                    "color": "#696969",
                    "fontFamily":"arial",
                    "bold":"true"
                  },
                  "children": "INTERNSHIP DESCRIPTION"
                }
              ],
              "props": {
                "flexDirection": "column",
                "justifyContent": "center",
                "height": 27
              }
            },
            {
              "component": "Box",
              "props": {
                "height": 2,
                "backgroundColor":"black"
              }
            },
            {
              "component": "Box",
              "children": [{
                "component": "Text",
                "props": {
                  "color": "black",
                  "size":"xs"
                },
                "children": "Opportunity to learn Docker and Kubernetes"
              }],
              "props": {
                "backgroundColor": "white",
                "flexDirection": "column",
                "justifyContent": "center",
                "width":"100%",
                "height": 70
              }
            },
            {
              "component": "Box",
              "props": {
                "height": 2,
                "backgroundColor":"black"
              }
            },
            {
              "component": "Box",
              "children": [
                {
                  "component": "Text",
                  "props": {
                    "size": "xs",
                    "color": "#696969",
                    "fontFamily":"arial",
                    "bold":"true"
                  },
                  "children": "LEARNING OUTCOMES"
                }
              ],
              "props": {
                "flexDirection": "column",
                "justifyContent": "center",
                "height": 27
              }
            },
            {
              "component": "Box",
              "props": {
                "height": 2,
                "backgroundColor":"black"
              }
            },
            {
              "component": "Box",
              "children": [{
                "component": "Text",
                "props": {
                  "color": "black",
                  "size":"xs"
                },
                "children": "Opportunity to learn Docker and Kubernetes"
              }],
              "props": {
                "backgroundColor": "white",
                "flexDirection": "column",
                "justifyContent": "center",
                "width":"100%",
                "height": 70
              }
            }
          ]
      },
      {
        "component": "Container",
        "props": {
          "flexDirection" : "column"
        },
        "children": [
          {
            "component": "Box",
            "props": {
              "width":"100%",
              "backgroundColor":"white",
              "height":75
            },
            "children": [
              {
                "component": "Box",
                "props": {
                  "flexDirection": "row",
                  "justifyContent": "center",
                  "paddingLeft":"100px",
                  "paddingTop":"135px"
                },
                "children": [
                  {
                    "component": "Button",
                    "props": {
                      "size": "sm",
                      "fontFamily":"arial",
                      "borderColor":"darkgray",
                      "text":"Apply",
                      "fontWeight": "lighter",
                      "borderWidth":2,
                      "height": 50,
                      "width": 80
                    }
                  }
                ]
              }
            ]
          }
        ]
      }
    ]
  }
]
}
