{
  "layout": {
    "title": "Interns",
    "appColor": "white",
    "backgroundColor": "whitesmoke",
    "header": {
      "variant": "default"
    },
    "sidebar": {
      "variant": "default"
    }
  },
  "children": [
    {
      "component": "Box",
      "children": [
        {
          "component": "Table",
          "props": {
            "columns": [
              {
                "Header": "Actions",
                "accessor": "actions",
                "buttonComponent": [
                  {
                    "text": "Edit",
                    "layoutName": "user-profile",
                    "btnCode": "BTN_EDIT_INTERN"
                  },
                  {
                    "text": "View",
                    "layoutName": "user-profile",
                    "btnCode": "BTN_VIEW_INTERN"
                  }
              ]
              },
              {
                "Header": "Full Name",
                "accessor": "firstName",
                "id": "firstName",
                "key": "firstName",
                "filterType": "string"
              },
              {
                "Header": "Edu Provider",
                "accessor": "eduProvider",
                "filterType": "string"
              },
              {
                "Header": "Mobile Phone",
                "accessor": "mobilePhone",
                "filterType": "number"
              },
              {
                "Header": "Username",
                "accessor": "uname",
                "filterType": "string"
              }
            ],
            "tableBackgroundColor": "#cccccc",
            "data": "_query.tableData",
            "height": "500px",
            "width": "500px",
            "itemsPerPage": 15
          }
        }
      ]
    }
  ],
  "query": [
    {
      "operator": "getBE",
      "id": "GRP_INTERNS",
      "as": "internList"
    },
    {
      "operator": "scope",
      "path": "internList.links",
      "as": "internList",
      "scope": {
        "operator": "getBE",
        "basePath": "baseEntities.data",
        "id": "{{link.targetCode}}",
        "as": "be"
      }
    },
    {
      "operator": "scope",
      "path": "internList",
      "scope": {
        "operator": "scope",
        "path": "be",
        "scope": {
          "operator": "populateBEGAttributes",
          "as": "attributes"
        }
      }
    },
    {
      "operator": "scope",
      "path": "internList",
      "scope": {
        "operator": "getBE",
        "as" : "company",
        "basePath": "baseEntities.data",
        "id": "{{be.attributes.LNK_EDU_PROVIDER.value}}"
      }
    },
    {
      "operator": "scope",
      "path": "internList",
      "as": "tableData",
      "scope": {
        "operator": "map",
        "fields": {
          "firstName": "be.attributes.PRI_NAME.value",
          "eduProvider": "company.name",
          "mobilePhone": "be.attributes.PRI_MOBILE.value",
          "uname": "be.attributes.PRI_USERNAME.value",
          "attributeCode": "code"
        }
      }
    }
  ]
}
