{
  "layout": {
    "title": "Registration",
    "appColor": "red",
    "backgroundColor": "white"
  },
  "children": [
  {  
    "component":"Box",
    "props":{
      "flexDirection":"row",
      "width": "100%",
      "height": "100vh",
      "backgroundColor":"white" 
    },
    "children": [
      {
        "component": "Box",
        "props": {
          "flex":1,
          "backgroundColor": "white",
          "alignItems":"center",
          "justifyContent":"center",
          "style": {
            "flex": 1
          },
          "contentContainerStyle": {
            "flex": 1
          }
        },
        "children":
          {
            "component": "Box",
            "props": {
              "flexDirection": "column",
              "alignItems": "center",
              "justifyContent": "flex-start",
              "flex": 1
            },
            "children": [
              {
                "component": "Image",
                "props": {
                  "width":"82%",
                  "source": "https://bouncer.outcome-hub.com/auth/resources/3.4.0.final/login/pcss/img/logo.png"
                }
              },
              {
                "component": "Box",
                "props": {
                  "flex": 2,
                  "flexShrink": 0,
                  "flexDirection": "column",
                  "marginTop":"55px"
                },
                "children":
                  {
                    "component": "Box",
                    "props": {
                      "alignItems": "center",
                      "justifyContent": "center",
                      "flex": 1
                    },
                    "children": 
                      {
                        "component": "AuthenticationForm",
                        "props": {
                          "type": "login"
                        },
                        "children": 
                          {
                            "component": "Box",
                            "props": {
                              "flexGrow": 1,
                              "flexShrink": 0,
                              "flexDirection": "column",
                              "justifyContent": "space-between",
                              "width": "80%"
                            },
                            "children": [
                              {
                                "component": "Box",
                                "props": {
                                  "flexDirection": "column"
                                },
                                "children": [
                                  {
                                    "component":"Box",
                                    "props":{
                                      "alignItems":"center",
                                      "justifyContent":"center"
                                    },
                                    "children":                                  {
                                      "component": "Heading",
                                      "props": {
                                        "color": "#696969",
                                        "size": "lg",
                                        "bold": false
                                      },
                                      "children": "RESET YOUR PASSWORD"
                                    }
                                  },
                                  {
                                    "component": "Box",
                                    "props": {
                                      "flexDirection": "column",
                                      "marginBottom": "20px"
                                    },
                                    "children": [
                                      {
                                        "component": "FormGenericInput",
                                        "useThemeFrom": "Input",
                                        "variant": "default",
                                        "props": {
                                          "marginTop": "15px",
                                          "type": "text",
                                          "placeholder": "Email Address",
                                          "name": "username",
                                          "color": "#093f7f",
                                          "borderWidth":"1px",
                                          "borderColor":"#000000",
                                          "borderRadius":"5px",
                                          "backgroundColor":"#FFFFFF"
                                        }
                                      }
                                    ]
                                  }
                                ]
                              },
                              {
                                "component": "Box",
                                "props": {
                                  "flexDirection": "column"
                                },
                                "children": [
                                  {
                                    "component": "FormGenericSubmit",
                                    "props": {
                                      "color": "red",
                                      "text": "Send Reset Email",
                                      "textColor": "#fff",
                                      "size": "xl",
                                      "height": "50px",
                                      "width": "300px",
                                      "hoverProps": {
                                        "color": "#D34545",
                                        "textColor": "#ffffff"
                                      }
                                    }
                                  },
                                  {
                                    "component":"Box",
                                    "props":{
                                      "borderBottomWidth":1,
                                      "borderColor": "#333",
                                      "borderStyle": "solid",
                                      "marginTop":"30px",
                                      "width": 102
                                    },
                                    "children":{
                                      "component": "LinkButton",
                                      "props": {
                                        "text": "Back to login",
                                        "textColor": "#696969",
                                        "to": "/",
                                        "borderbottom": 1,
                                        "borderWidth":1,
                                        "borderColor": "#e3e3e3",
                                        "paddingX": 0,
                                        "paddingY": 0,
                                        "hoverProps": {
                                          "textColor": "#696969"
                                        }
                                      }
                                    }
                                  }
                                ]
                              }
                            ]
                          }
                      }
                  }
              }
            ]
          }
      },
      {
        "component": "Box",
        "props": {
          "flex":"1.5",
          "flexDirection" : "column",
          "width": "100%"
        },
        "children": [
          {
            "component": "Box",
            "props": { 
              "height":"100%",
              "width": "100%"
            },
            "children": [
              {
                "component": "Image",
                "props": {
                  "flex":1,
                  "height":"100%",
                  "width": "100%",
                  "minWidth": "100%",
                  "resizeMode": "cover",
                  "source": "https://images.pexels.com/photos/869258/pexels-photo-869258.jpeg?cs=srgb&dl=adventure-alpine-climb-869258.jpg&fm=jpghttps://images.pexels.com/photos/372101/pexels-photo-372101.jpeg?cs=srgb&dl=adventure-astronomy-constellation-372101.jpg&fm=jpg",
                  "justifyContent":"center",
                  "flexDirection":"column"
                }
              }
            ]
          }
        ]
      }
    ]
  }
]
}