{
  "Grid": {
    "rows": 2,
    "cols": 1,
    "style": {
      "padding": "10px",
      "background": "white",
      "fontsize": "10px"
    },
    "children": [{
        "Grid": {
          "position": [
            0,
            0
          ],
          "rows": 1,
          "cols": [
            1,
            1,
            "10px"
          ],
          "children": [{
              "imageview": {
                "position": [
                  0,
                  0
                ],
                "style": {
                  "margin": "0px",
                  "maxwidth": "40px",
                  "width": "40px"
                },
                "src": "be.link.applicant.pri_image_url"
              }
            },
            {
              "Grid": {
                "position": [
                  0,
                  1
                ],
                "rows": 2,
                "cols": 1,
                "children": [{
                    "p": {
                      "position": [
                        0,
                        0
                      ],
                      "style": {
                        "margin": "0px"
                      },
                      "children": "be.pri_applicant_fullname"
                    }
                  },
                  {
                    "p": {
                      "position": [
                        1,
                        0
                      ],
                      "style": {
                        "margin": "0px"
                      },
                      "children": "be.pri_applicant_username"
                    }
                  }
                ]
              }
            },
            {
              "gennystatus": {
                "position": [
                  0,
                  2
                ],
                "root": "be.code",
                "style": {
                  "height": "25px",
                  "width": "10px"
                },
                "statusstyle": {
                  "height": "100%",
                  "width": "10px",
                  "maxheight": "40px"
                }
              }
            }
          ]
        }
      },
      {
        "selector": {
          "position": [
            1,
            0
          ],
          "checkvalues": [
            "user.pri_is_buyer"
          ],
          "showvalues": [
            true
          ],
          "children": [{
            "gennybutton": {
              "style": {
                "height": "30px",
                "margintop": "10px"
              },
              "buttonstyle": {
                "background": "project.pri_color"
              },
              "children": "view my application",
              "buttoncode": "btn_view_application",
              "value": {
                "itemcode": "be.code",
                "hint": "root"
              }
            }
          }]
        }
      },
      {
        "selector": {
          "position": [
            1,
            0
          ],
          "checkvalues": [
            "user.pri_is_seller"
          ],
          "showvalues": [
            true
          ],
          "children": [{
            "gennybutton": {
              "style": {
                "height": "30px",
                "margintop": "10px"
              },
              "buttonstyle": {
                "background": "project.pri_color"
              },
              "children": "view application",
              "buttoncode": "btn_view_application",
              "value": {
                "itemcode": "be.code",
                "hint": "root"
              }
            }
          }]
        }
      },
      {
        "selector": {
          "position": [
            1,
            0
          ],
          "checkvalues": [
            "root"
          ],
          "showvalues": [
            "grp_applied"
          ],
          "children": [{
            "selector": {
              "checkvalues": [
                "user.pri_is_buyer"
              ],
              "hidevalues": [
                true
              ],
              "children": [{
                "gennybutton": {
                  "style": {
                    "height": "30px",
                    "margintop": "10px"
                  },
                  "buttonstyle": {
                    "background": "project.pri_color"
                  },
                  "children": "shortlist",
                  "buttoncode": "btn_shortlist_application",
                  "value": {
                    "itemcode": "be.code",
                    "hint": "root"
                  }
                }
              }]
            }
          }]
        }
      },
      {
        "selector": {
          "position": [
            1,
            0
          ],
          "checkvalues": [
            "user.pri_is_host_company"
          ],
          "showvalues": [
            "true"
          ],
          "children": [{
            "selector": {
              "position": [
                1,
                0
              ],
              "checkvalues": [
                "root"
              ],
              "showvalues": [
                "grp_shortlisted"
              ],
              "children": [{
                "gennybutton": {
                  "style": {
                    "height": "30px",
                    "margintop": "10px"
                  },
                  "buttonstyle": {
                    "backgroundcolor": "project.pri_color"
                  },
                  "children": "interview",
                  "buttoncode": "btn_interview_application",
                  "value": {
                    "itemcode": "be.code",
                    "hint": "root"
                  }
                }
              }]
            }
          }]
        }
      },
      {
        "selector": {
          "position": [
            1,
            0
          ],
          "checkvalues": [
            "root"
          ],
          "showvalues": [
            "grp_shortlisted"
          ],
          "children": [{
            "selector": {
              "checkvalues": [
                "user.pri_is_buyer"
              ],
              "hidevalues": [
                true
              ],
              "children": [{
                "gennybutton": {
                  "style": {
                    "height": "30px",
                    "margintop": "10px"
                  },
                  "buttonstyle": {
                    "background": "#cb4b16"
                  },
                  "children": "reject",
                  "buttoncode": "btn_reject_application",
                  "value": {
                    "itemcode": "be.code",
                    "hint": "root"
                  }
                }
              }]
            }
          }]
        }
      },
      {
        "selector": {
          "position": [
            1,
            0
          ],
          "checkvalues": [
            "root"
          ],
          "showvalues": [
            "grp_interviews"
          ],
          "children": [{
            "selector": {
              "checkvalues": [
                "user.pri_is_buyer"
              ],
              "hidevalues": [
                true
              ],
              "children": [{
                "gennybutton": {
                  "style": {
                    "height": "30px",
                    "margintop": "10px"
                  },
                  "buttonstyle": {
                    "background": "project.pri_color"
                  },
                  "children": "make offer",
                  "buttoncode": "btn_offer_application",
                  "value": {
                    "itemcode": "be.code",
                    "hint": "root"
                  }
                }
              }]
            }
          }]
        }
      },
      {
        "selector": {
          "position": [
            1,
            0
          ],
          "checkvalues": [
            "root"
          ],
          "showvalues": [
            "grp_offered"
          ],
          "children": [{
            "gennybutton": {
              "style": {
                "height": "30px",
                "margintop": "10px"
              },
              "buttonstyle": {
                "background": "green"
              },
              "children": "view internship offer",
              "buttoncode": "btn_show_compliance_document",
              "value": {
                "itemcode": "be.code",
                "hint": "root"
              }
            }
          }]
        }
      },
      {
        "selector": {
          "position": [
            1,
            0
          ],
          "checkvalues": [
            "root"
          ],
          "showvalues": [
            "grp_placed"
          ],
          "children": [{
            "selector": {
              "checkvalues": [
                "user.pri_is_buyer"
              ],
              "hidevalues": [
                true
              ],
              "children": [{
                "gennybutton": {
                  "style": {
                    "height": "30px",
                    "margintop": "10px"
                  },
                  "buttonstyle": {
                    "background": "blue"
                  },
                  "children": "start internship",
                  "buttoncode": "btn_start_internship",
                  "value": {
                    "itemcode": "be.code",
                    "hint": "root"
                  }
                }
              }]
            }
          }]
        }
      },
      {
        "selector": {
          "position": [
            1,
            0
          ],
          "checkvalues": [
            "root"
          ],
          "showvalues": [
            "grp_in_progress"
          ],
          "children": [{
            "selector": {
              "checkvalues": [
                "user.pri_is_buyer"
              ],
              "hidevalues": [
                true
              ],
              "children": [{
                "gennybutton": {
                  "style": {
                    "height": "30px",
                    "margintop": "10px"
                  },
                  "buttonstyle": {
                    "background": "orange"
                  },
                  "children": "finish internship",
                  "buttoncode": "btn_finish_internship",
                  "value": {
                    "itemcode": "be.code",
                    "hint": "root"
                  }
                }
              }]
            }
          }]
        }
      },
      {
        "selector": {
          "position": [
            1,
            0
          ],
          "checkvalues": [
            "be.pri_is_deactivated"
          ],
          "showvalues": [
            true
          ],
          "children": [{
            "selector": {
              "checkvalues": [
                "user.pri_is_buyer"
              ],
              "hidevalues": [
                true
              ],
              "children": [{
                "gennybutton": {
                  "style": {
                    "height": "30px",
                    "margintop": "10px"
                  },
                  "buttonstyle": {
                    "background": "green"
                  },
                  "children": "reactivate",
                  "buttoncode": "btn_activate_application",
                  "value": {
                    "itemcode": "be.code",
                    "hint": "root"
                  }
                }
              }]
            }
          }]
        }
      },
      {
        "selector": {
          "position": [
            1,
            0
          ],
          "checkvalues": [
            "be.pri_is_deactivated"
          ],
          "hidevalues": [
            true
          ],
          "children": [{
            "selector": {
              "checkvalues": [
                "user.pri_is_buyer"
              ],
              "hidevalues": [
                true
              ],
              "children": [{
                "gennybutton": {
                  "style": {
                    "height": "30px",
                    "margintop": "10px"
                  },
                  "buttonstyle": {
                    "background": "#444444"
                  },
                  "children": "on hold",
                  "buttoncode": "btn_deactivate_application",
                  "value": {
                    "itemcode": "be.code",
                    "hint": "root"
                  }
                }
              }]
            }

          }]
        }
      }
    ]
  }
}
