{
    "GennyButton":{
        "style":{
            "width":"100px",
            "height":"30px",
            "marginBottom":"20px"
        },
        "buttonStyle":{
            "height":"30px",
            "padding":"0"
        },
        "buttonCode":"BTN_GO_BACK_JOB_DETAIL",
        "hint":{
            "itemCode":"BE.code"
        },
        "children":[
            {
                "IconSmall":{
                    "style":{
                        "fontSize":"28px",
                        "transform":"rotate(90deg)",
                        "color":"white"
                    },
                    "name":"arrow_drop_down"
                }
            },
            {
                "span":{
                    "style":{
                        "color":"white"
                    },
                    "children":"BACK"
                }
            }
        ]
    }
}
